CellClear/__init__.py
CellClear/base_cli.py
CellClear/correct_expression/__init__.py
CellClear/correct_expression/argparser.py
CellClear/correct_expression/cli.py
CellClear/correct_expression/correct_expression.py
CellClear/correct_expression/plot.py
CellClear/correct_expression/utils.py
CellClear-0.1.0.dist-info/LICENSE
CellClear-0.1.0.dist-info/METADATA
CellClear-0.1.0.dist-info/WHEEL
CellClear-0.1.0.dist-info/entry_points.txt
CellClear-0.1.0.dist-info/top_level.txt
CellClear-0.1.0.dist-info/RECORD
