Metadata-Version: 2.1
Name: CellClear
Version: 0.1.0
Summary: Estimating and removing ambient expression in scRNA-seq data
Author: Wanxiang Huang
License: BSD 3-Clause License
Keywords: scRNA-seq,bioinformatics
Classifier: Development Status :: 3 - Alpha
Classifier: Intended Audience :: Science/Research
Classifier: License :: OSI Approved :: BSD License
Classifier: Programming Language :: Python :: 3
Classifier: Programming Language :: Python :: 3.9
Classifier: Programming Language :: Python :: 3.10
Classifier: Programming Language :: Python :: 3.11
Classifier: Programming Language :: Python :: 3.12
Classifier: Topic :: Scientific/Engineering :: Bio-Informatics
Requires-Python: >=3.9
License-File: LICENSE
Requires-Dist: pandas
Requires-Dist: numpy
Requires-Dist: scipy
Requires-Dist: scanpy ==1.9.3
Requires-Dist: leidenalg
Requires-Dist: anndata >=0.8.0
Requires-Dist: scikit-learn
Requires-Dist: statsmodels
Requires-Dist: statannot ==0.2.3
Requires-Dist: seaborn ==0.11.2
Requires-Dist: harmonypy
